{
  "filename": "CON_D_0011434.wav",
  "prediction": "Fake",
  "summary": {
    "num_regions": 109,
    "largest_region_area": 8221,
    "total_evidence_area": 15636,
    "max_importance": 0.572
  },
  "regions": [
    {
      "rank": 1,
      "time_start": 0.032,
      "time_end": 0.67,
      "freq_low": 0.0,
      "freq_high": 8000.0,
      "centroid": {
        "time": 0.319,
        "frequency": 4039.6
      },
      "importance": 0.572,
      "mean_importance": 0.287,
      "max_importance": 1.0,
      "area_px": 8221,
      "supporting_scores": {
        "refined_ig": {
          "mean": 0.084,
          "max": 1.0
        },
        "refined_saliency": {
          "mean": 0.009,
          "max": 0.543
        },
        "refined_lime": {
          "mean": 0.724,
          "max": 1.0
        }
      }
    },
    {
      "rank": 2,
      "time_start": 5.553,
      "time_end": 5.585,
      "freq_low": 1715.4,
      "freq_high": 1886.9,
      "centroid": {
        "time": 5.553,
        "frequency": 1793.4
      },
      "importance": 0.561,
      "mean_importance": 0.501,
      "max_importance": 0.651,
      "area_px": 11,
      "supporting_scores": {
        "refined_ig": {
          "mean": 0.016,
          "max": 0.023
        },
        "refined_saliency": {
          "mean": 0.748,
          "max": 1.0
        },
        "refined_lime": {
          "mean": 0.305,
          "max": 0.305
        }
      }
    },
    {
      "rank": 3,
      "time_start": 6.99,
      "time_end": 7.117,
      "freq_low": 3571.2,
      "freq_high": 5130.6,
      "centroid": {
        "time": 7.065,
        "frequency": 4350.4
      },
      "importance": 0.504,
      "mean_importance": 0.27,
      "max_importance": 0.854,
      "area_px": 202,
      "supporting_scores": {
        "refined_ig": {
          "mean": 0.001,
          "max": 0.002
        },
        "refined_saliency": {
          "mean": 0.163,
          "max": 0.91
        },
        "refined_lime": {
          "mean": 0.586,
          "max": 0.64
        }
      }
    },
    {
      "rank": 4,
      "time_start": 6.319,
      "time_end": 6.607,
      "freq_low": 670.6,
      "freq_high": 2963.0,
      "centroid": {
        "time": 6.46,
        "frequency": 1887.5
      },
      "importance": 0.469,
      "mean_importance": 0.267,
      "max_importance": 0.772,
      "area_px": 754,
      "supporting_scores": {
        "refined_ig": {
          "mean": 0.173,
          "max": 0.788
        },
        "refined_saliency": {
          "mean": 0.005,
          "max": 0.057
        },
        "refined_lime": {
          "mean": 0.558,
          "max": 0.654
        }
      }
    },
    {
      "rank": 5,
      "time_start": 6.99,
      "time_end": 7.117,
      "freq_low": 7547.8,
      "freq_high": 8000.0,
      "centroid": {
        "time": 7.059,
        "frequency": 7791.5
      },
      "importance": 0.461,
      "mean_importance": 0.317,
      "max_importance": 0.679,
      "area_px": 70,
      "supporting_scores": {
        "refined_ig": {
          "mean": 0.001,
          "max": 0.004
        },
        "refined_saliency": {
          "mean": 0.23,
          "max": 0.675
        },
        "refined_lime": {
          "mean": 0.571,
          "max": 0.64
        }
      }
    }
  ]
}